LICENSE.txt
README.md
setup.py
rocket_V1/__init__.py
rocket_V1/rocket_V1.py
rocket_V1.egg-info/PKG-INFO
rocket_V1.egg-info/SOURCES.txt
rocket_V1.egg-info/dependency_links.txt
rocket_V1.egg-info/requires.txt
rocket_V1.egg-info/top_level.txt