Metadata-Version: 2.4
Name: rocket_V1
Version: 1.0.0
Summary: An awesome package that does something
Home-page: http://pypi.python.org/pypi/<your_package_name>/
Author: Fezz Amina
Author-email: khadidjafezazi21@gmail.com
License: LICENSE.txt
License-File: LICENSE.txt
Requires-Dist: rocket_V1
Dynamic: author
Dynamic: author-email
Dynamic: description
Dynamic: description-content-type
Dynamic: home-page
Dynamic: license
Dynamic: license-file
Dynamic: requires-dist
Dynamic: summary
